homework_4/ALU.v
module ALU 
(
    input [63:0] data1_i,
    input [63:0] data2_i,
    input [3:0] ALUCtrl_i,
    output reg [63:0] data_o
);

always @(*) begin
    if (ALUCtrl_i == 4'b0000) begin
        data_o = data1_i + data2_i; // add
    end else if (ALUCtrl_i == 4'b0001) begin
        data_o = data1_i - data2_i; // sub
    end else if (ALUCtrl_i == 4'b0010) begin
        data_o = data1_i ^ data2_i; // xor
    end else if (ALUCtrl_i == 4'b0011) begin
        data_o = data1_i | data2_i; // or
    end else if (ALUCtrl_i == 4'b0100) begin
        data_o = data1_i & data2_i; // and
    end else if (ALUCtrl_i == 4'b0101) begin
        data_o = data1_i << (data2_i[5:0]); // sll
    end else if (ALUCtrl_i == 4'b0110) begin
        data_o = data1_i >> (data2_i[5:0]); // srl
    end else if (ALUCtrl_i == 4'b0111) begin
        data_o = $signed(data1_i) >>> (data2_i[5:0]); // sra
    end else if (ALUCtrl_i == 4'b1000) begin
        data_o = data1_i + data2_i; // addi
    end else if (ALUCtrl_i == 4'b1001) begin
        data_o = data1_i ^ data2_i; // xori
    end else if (ALUCtrl_i == 4'b1010) begin
        data_o = data1_i | data2_i; // ori
    end else if (ALUCtrl_i == 4'b1011) begin
        data_o = data1_i & data2_i; // andi
    end else if (ALUCtrl_i == 4'b1100) begin
        data_o = data1_i << (data2_i[5:0]); // slli
    end else if (ALUCtrl_i == 4'b1101) begin
        data_o = data1_i >> (data2_i[5:0]); // srli
    end else if (ALUCtrl_i == 4'b1110) begin
        data_o = $signed(data1_i) >>> (data2_i[5:0]); // srai
    end
end

endmodule

homework_4/ALUControl.v
module ALUControl 
(
    input [1:0] ALUOp_i,
    input [2:0] funct3_i,
    input [6:0] funct7_i,
    output reg [3:0] ALUCtrl_o
);

// ALUOp_i -> 10:R-type 11:I-type

always @(*) begin
    if (ALUOp_i == 2'b10) begin // R-type
        if (funct3_i == 3'b000) begin
            if (funct7_i == 7'b0000000) begin
                ALUCtrl_o = 4'b0000; // add
            end else if (funct7_i == 7'b0100000) begin
                ALUCtrl_o = 4'b0001; // sub
            end
        end
        if (funct3_i == 3'b100) begin
            ALUCtrl_o = 4'b0010; // xor
        end
        if (funct3_i == 3'b110) begin
            ALUCtrl_o = 4'b0011; // or
        end
        if (funct3_i == 3'b111) begin
            ALUCtrl_o = 4'b0100; // and
        end
        if (funct3_i == 3'b001) begin
            ALUCtrl_o = 4'b0101; // sll
        end
        if (funct3_i == 3'b101) begin
            if (funct7_i == 7'b0000000) begin
                ALUCtrl_o = 4'b0110; // srl
            end else if (funct7_i == 7'b0100000) begin
                ALUCtrl_o = 4'b0111; // sra 
            end
        end
    end else if (ALUOp_i == 2'b11) begin // I-type
        if (funct3_i == 3'b000) begin 
            ALUCtrl_o = 4'b1000; // addi
        end
        if (funct3_i == 3'b100) begin
            ALUCtrl_o = 4'b1001; // xori
        end
        if (funct3_i == 3'b110) begin
            ALUCtrl_o = 4'b1010; // ori
        end
        if (funct3_i == 3'b111) begin
            ALUCtrl_o = 4'b1011; // andi
        end
        if (funct3_i == 3'b001) begin
            ALUCtrl_o = 4'b1100; // slli 
        end
        if (funct3_i == 3'b101) begin
            if (funct7_i[6:1] == 6'b000000) begin
                ALUCtrl_o = 4'b1101; // srli
            end else if (funct7_i[6:1] == 6'b010000) begin
                ALUCtrl_o = 4'b1110; // srai
            end
        end
    end
end

endmodule

homework_4/ImmGen.v
module ImmGen
(
    input [31:0] instruction_i,
    output reg [63:0] immediate_o
);

always @(*) begin
    if (instruction_i[6:0] == 7'b0010011) begin
        if (instruction_i[14:12] == 3'b001) begin
            immediate_o = {58'b0, instruction_i[25:20]};
        end else if (instruction_i[14:12] == 3'b101) begin
            immediate_o = {58'b0, instruction_i[25:20]};
        end else begin
            immediate_o = {{52{instruction_i[31]}}, instruction_i[31:20]};
        end
    end
end

endmodule

homework_4/Control.v
module Control 
(
    input [6:0] opcode_i, // 7 bits opcode
    output reg [1:0] ALUOp_o, // 10:R-type 11:I-type
    output reg ALUSrc_o, // 0:register 1:imm
    output reg RegWrite_o // 1:WB register
);

always @(*) begin
    if (opcode_i == 7'b0110011) begin // R-type
        ALUOp_o = 2'b10;
        ALUSrc_o = 1'b0;
        RegWrite_o = 1'b1;
    end else if (opcode_i == 7'b0010011) begin // I-type
        ALUOp_o = 2'b11;
        ALUSrc_o = 1'b1;
        RegWrite_o = 1'b1;
    end
end

endmodule

homework_4/Registers.v
module Registers
( // Do not modify port names
    input         clk_i,
    input         rst_i,
    input  [4:0]  RS1addr_i,
    input  [4:0]  RS2addr_i,
    input  [4:0]  RDaddr_i,
    input  [63:0] RDdata_i,
    input         RegWrite_i,
    output [63:0] RS1data_o, 
    output [63:0] RS2data_o
);

// Store the content of registers here.
// Do not change the name.
reg signed [63:0] register [0:31];

// TODO: Implement your register file here.
// All registers should be reset to 0 when rst_i is high.
// Make sure that register[0] is always 0.
assign RS1data_o = (RS1addr_i == 5'b0) ? 64'b0 : register[RS1addr_i];
assign RS2data_o = (RS2addr_i == 5'b0) ? 64'b0 : register[RS2addr_i];

integer i;

always @(posedge clk_i or posedge rst_i) begin
    if (rst_i) begin
        for (i = 0; i < 32; i = i + 1) begin
            register[i] <= 64'b0;
        end
    end else if (RegWrite_i != 1'b0 && RDaddr_i != 5'b0) begin
        register[RDaddr_i] <= RDdata_i;
    end
end

endmodule

homework_4/PC.v
module PC
(   // Do not modify port names
    input             clk_i,
    input             rst_i,
    input      [63:0] pc_i,
    output reg [63:0] pc_o
);

// TODO: Implement your PC here.
// PC should be reset to 0 when rst_i is high.
always @(posedge clk_i or posedge rst_i) begin
    if (rst_i) begin
        pc_o <= 64'b0;
    end else begin
        pc_o <= pc_i;
    end
end

endmodule

homework_4/Instruction_Memory.v
module Instruction_Memory
(
    input  [63:0] addr_i,
    output [31:0] instr_o
);

// Instruction memory
// DO NOT MODIFY THIS MODULE

reg [31:0] memory [0:1024];

assign  instr_o = memory[addr_i >> 2];

endmodule

homework_4/CPU.v
module CPU
(
    input clk_i, 
    input rst_i
);

// TODO: Implement your CPU here
wire [63:0] ProgramCounter, NextPc, Immediate, ALUresult, RS1data, RS2data;
wire [31:0] Instruction;
wire [3:0] ALUCtrl;
wire [1:0] ALUOp;
wire ALUSrc, RegWrite;

// Do not change the name of these module instances.
Instruction_Memory Instruction_Memory(
    .addr_i     (ProgramCounter), 
    .instr_o    (Instruction)
);

PC PC(
    .clk_i      (clk_i),
    .rst_i      (rst_i),
    .pc_i       (NextPc),
    .pc_o       (ProgramCounter)
);

Registers Registers(
    .clk_i      (clk_i),
    .rst_i      (rst_i),
    .RS1addr_i  (Instruction[19:15]),
    .RS2addr_i  (Instruction[24:20]),
    .RDaddr_i   (Instruction[11:7]), 
    .RDdata_i   (ALUresult),
    .RegWrite_i (RegWrite), 
    .RS1data_o  (RS1data), 
    .RS2data_o  (RS2data) 
);

// Control
Control Control(
    .opcode_i(Instruction[6:0]),
    .ALUOp_o(ALUOp),
    .ALUSrc_o(ALUSrc),
    .RegWrite_o(RegWrite)
);

// ImmGen
ImmGen ImmGen(
    .instruction_i(Instruction),
    .immediate_o(Immediate)
);

// ALUControl
ALUControl ALUControl(
    .ALUOp_i(ALUOp),
    .funct3_i(Instruction[14:12]),
    .funct7_i(Instruction[31:25]),
    .ALUCtrl_o(ALUCtrl)
);

// ALU
ALU ALU(
    .data1_i(RS1data),
    .data2_i(ALUSrc ? Immediate : RS2data),
    .ALUCtrl_i(ALUCtrl),
    .data_o(ALUresult)
);

assign NextPc = ProgramCounter + 64'd4;

endmodule

homework_4/Testbench.v
`define CYCLE_TIME 50
`timescale 1ns/1ps

module Testbench;

integer i;
integer outfile;
integer cycles = 0;
reg     clk = 0;
reg     rst = 1;

CPU CPU(
    .clk_i(clk),
    .rst_i(rst)
);

always #(`CYCLE_TIME/2) clk = ~clk;

initial begin
    $dumpfile("CPU.vcd");
    $dumpvars;
    outfile = $fopen("output.txt") | 1;

    /* Initialize the instruction memory
       32'h00000013 = NOP (addi x0, x0, 0) */
    for (i = 0; i < 1024; i = i + 1)
        CPU.Instruction_Memory.memory[i] = 32'h00000013;

    $readmemb("instruction.txt", CPU.Instruction_Memory.memory);

    #(`CYCLE_TIME/4) rst = 0;
end

always @(posedge clk) begin
    // Stop after 30 cycles
    if(cycles == 30)
        $finish;

    cycles = cycles + 1;

    $fdisplay(outfile, "PC  = %d", CPU.PC.pc_o);
    $fdisplay(outfile, "x0  = %d, x1  = %d", CPU.Registers.register[0], CPU.Registers.register[1]);
    $fdisplay(outfile, "x2  = %d, x3  = %d", CPU.Registers.register[2], CPU.Registers.register[3]);
    $fdisplay(outfile, "x4  = %d, x5  = %d", CPU.Registers.register[4], CPU.Registers.register[5]);
    $fdisplay(outfile, "x6  = %d, x7  = %d", CPU.Registers.register[6], CPU.Registers.register[7]);
    $fdisplay(outfile, "x8  = %d, x9  = %d", CPU.Registers.register[8], CPU.Registers.register[9]);
    $fdisplay(outfile, "x10 = %d, x11 = %d", CPU.Registers.register[10], CPU.Registers.register[11]);
    $fdisplay(outfile, "x12 = %d, x13 = %d", CPU.Registers.register[12], CPU.Registers.register[13]);
    $fdisplay(outfile, "x14 = %d, x15 = %d", CPU.Registers.register[14], CPU.Registers.register[15]);
    $fdisplay(outfile, "x16 = %d, x17 = %d", CPU.Registers.register[16], CPU.Registers.register[17]);
    $fdisplay(outfile, "x18 = %d, x19 = %d", CPU.Registers.register[18], CPU.Registers.register[19]);
    $fdisplay(outfile, "x20 = %d, x21 = %d", CPU.Registers.register[20], CPU.Registers.register[21]);
    $fdisplay(outfile, "x22 = %d, x23 = %d", CPU.Registers.register[22], CPU.Registers.register[23]);
    $fdisplay(outfile, "x24 = %d, x25 = %d", CPU.Registers.register[24], CPU.Registers.register[25]);
    $fdisplay(outfile, "x26 = %d, x27 = %d", CPU.Registers.register[26], CPU.Registers.register[27]);
    $fdisplay(outfile, "x28 = %d, x29 = %d", CPU.Registers.register[28], CPU.Registers.register[29]);
    $fdisplay(outfile, "x30 = %d, x31 = %d", CPU.Registers.register[30], CPU.Registers.register[31]);
    $fdisplay(outfile, "\n");
end

endmodule

homework_4/CPU.vcd
$date
	Mon Jun 23 21:41:02 2025
$end
$version
	Icarus Verilog
$end
$timescale
	1ps
$end
$scope module Testbench $end
$var reg 1 ! clk $end
$var reg 1 " rst $end
$var integer 32 # cycles [31:0] $end
$var integer 32 $ i [31:0] $end
$var integer 32 % outfile [31:0] $end
$scope module CPU $end
$var wire 1 ! clk_i $end
$var wire 1 " rst_i $end
$var wire 1 & RegWrite $end
$var wire 64 ' RS2data [63:0] $end
$var wire 64 ( RS1data [63:0] $end
$var wire 64 ) ProgramCounter [63:0] $end
$var wire 64 * NextPc [63:0] $end
$var wire 32 + Instruction [31:0] $end
$var wire 64 , Immediate [63:0] $end
$var wire 64 - ALUresult [63:0] $end
$var wire 1 . ALUSrc $end
$var wire 2 / ALUOp [1:0] $end
$var wire 4 0 ALUCtrl [3:0] $end
$scope module ALU $end
$var wire 64 1 data2_i [63:0] $end
$var wire 64 2 data1_i [63:0] $end
$var wire 4 3 ALUCtrl_i [3:0] $end
$var reg 64 4 data_o [63:0] $end
$upscope $end
$scope module ALUControl $end
$var wire 3 5 funct3_i [2:0] $end
$var wire 7 6 funct7_i [6:0] $end
$var wire 2 7 ALUOp_i [1:0] $end
$var reg 4 8 ALUCtrl_o [3:0] $end
$upscope $end
$scope module Control $end
$var wire 7 9 opcode_i [6:0] $end
$var reg 2 : ALUOp_o [1:0] $end
$var reg 1 . ALUSrc_o $end
$var reg 1 & RegWrite_o $end
$upscope $end
$scope module ImmGen $end
$var wire 32 ; instruction_i [31:0] $end
$var reg 64 < immediate_o [63:0] $end
$upscope $end
$scope module Instruction_Memory $end
$var wire 32 = instr_o [31:0] $end
$var wire 64 > addr_i [63:0] $end
$upscope $end
$scope module PC $end
$var wire 1 ! clk_i $end
$var wire 64 ? pc_i [63:0] $end
$var wire 1 " rst_i $end
$var reg 64 @ pc_o [63:0] $end
$upscope $end
$scope module Registers $end
$var wire 5 A RDaddr_i [4:0] $end
$var wire 64 B RDdata_i [63:0] $end
$var wire 5 C RS1addr_i [4:0] $end
$var wire 5 D RS2addr_i [4:0] $end
$var wire 1 & RegWrite_i $end
$var wire 1 ! clk_i $end
$var wire 1 " rst_i $end
$var wire 64 E RS2data_o [63:0] $end
$var wire 64 F RS1data_o [63:0] $end
$var integer 32 G i [31:0] $end
$upscope $end
$upscope $end
$upscope $end
$enddefinitions $end
$comment Show the parameter values. $end
$dumpall
$end
#0
$dumpvars
b100000 G
b0 F
b0 E
b101 D
b0 C
b101 B
b0 A
b0 @
b100 ?
b0 >
b10100000000000000010011 =
b101 <
b10100000000000000010011 ;
b11 :
b10011 9
b1000 8
b11 7
b0 6
b0 5
b101 4
b1000 3
b0 2
b101 1
b1000 0
b11 /
1.
b101 -
b101 ,
b10100000000000000010011 +
b100 *
b0 )
b0 (
b0 '
1&
b11 %
b10000000000 $
b0 #
1"
0!
$end
#12000
0"
#25000
b1001 -
b1001 4
b1001 B
b1001 1
b1000 A
b1001 D
b1001 ,
b1001 <
b100100000000010000010011 +
b100100000000010000010011 ;
b100100000000010000010011 =
b1000 *
b1000 ?
b100 )
b100 >
b100 @
b1 #
1!
#50000
0!
#75000
b1111111111111111111111111111111111111111111111111111111010101010 -
b1111111111111111111111111111111111111111111111111111111010101010 4
b1111111111111111111111111111111111111111111111111111111010101010 B
b1001 (
b1001 2
b1001 F
b1111111111111111111111111111111111111111111111111111111010100001 1
b1110101 6
b101 A
b1 D
b1000 C
b1111111111111111111111111111111111111111111111111111111010100001 ,
b1111111111111111111111111111111111111111111111111111111010100001 <
b11101010000101000000001010010011 +
b11101010000101000000001010010011 ;
b11101010000101000000001010010011 =
b1100 *
b1100 ?
b1000 )
b1000 >
b1000 @
b10 #
1!
#100000
0!
#125000
b1111111111111111111111111111111111111111111111111111111110101010 -
b1111111111111111111111111111111111111111111111111111111110101010 4
b1111111111111111111111111111111111111111111111111111111110101010 B
b1110 0
b1110 3
b1110 8
b1111111111111111111111111111111111111111111111111111111010101010 (
b1111111111111111111111111111111111111111111111111111111010101010 2
b1111111111111111111111111111111111111111111111111111111010101010 F
b10 1
b100000 6
b101 5
b10 D
b101 C
b10 ,
b10 <
b1000000001000101101001010010011 +
b1000000001000101101001010010011 ;
b1000000001000101101001010010011 =
b10000 *
b10000 ?
b1100 )
b1100 >
b1100 @
b11 #
1!
#150000
0!
#175000
b1101 0
b1101 3
b1101 8
b1 1
b0 6
b110 A
b1 D
b1 ,
b1 <
b111111111111111111111111111111111111111111111111111111111010101 -
b111111111111111111111111111111111111111111111111111111111010101 4
b111111111111111111111111111111111111111111111111111111111010101 B
b100101101001100010011 +
b100101101001100010011 ;
b100101101001100010011 =
b1111111111111111111111111111111111111111111111111111111110101010 (
b1111111111111111111111111111111111111111111111111111111110101010 2
b1111111111111111111111111111111111111111111111111111111110101010 F
b10100 *
b10100 ?
b10000 )
b10000 >
b10000 @
b100 #
1!
#200000
0!
#225000
b111111111111111111111111111111111111111111111111111111111010101 1
b1000000000000000000000000000000000000000000000000000000000101011 -
b1000000000000000000000000000000000000000000000000000000000101011 4
b1000000000000000000000000000000000000000000000000000000000101011 B
b1 0
b1 3
b1 8
0.
b10 /
b10 7
b10 :
b111111111111111111111111111111111111111111111111111111111010101 '
b111111111111111111111111111111111111111111111111111111111010101 E
b0 (
b0 2
b0 F
b100000 6
b0 5
b110011 9
b110 D
b0 C
b1000000011000000000001100110011 +
b1000000011000000000001100110011 ;
b1000000011000000000001100110011 =
b11000 *
b11000 ?
b10100 )
b10100 >
b10100 @
b101 #
1!
#250000
0!
#275000
b1000 0
b1000 3
b1000 8
1.
b11 /
b11 7
b11 :
b1100001 -
b1100001 4
b1100001 B
b11 6
b10011 9
b111 A
b1 D
b1100001 ,
b1100001 <
b1100001 1
b110000100000000001110010011 +
b110000100000000001110010011 ;
b110000100000000001110010011 =
b0 '
b0 E
b11100 *
b11100 ?
b11000 )
b11000 >
b11000 @
b110 #
1!
#300000
0!
#325000
b1001000000000000000000000000000000000 -
b1001000000000000000000000000000000000 4
b1001000000000000000000000000000000000 B
b101 0
b101 3
b101 8
0.
b10 /
b10 7
b10 :
b1100001 '
b1100001 E
b1001 (
b1001 2
b1001 F
b0 6
b1 5
b110011 9
b1000 A
b111 D
b1000 C
b11101000001010000110011 +
b11101000001010000110011 ;
b11101000001010000110011 =
b100000 *
b100000 ?
b11100 )
b11100 >
b11100 @
b111 #
1!
#350000
0!
#375000
b1001000000000000000000000000000000000 1
b1 0
b1 3
b1 8
b1001000000000000000000000000000000000 '
b1001000000000000000000000000000000000 E
b100000 6
b0 5
b1000 D
b0 C
b1111111111111111111111111110111000000000000000000000000000000000 -
b1111111111111111111111111110111000000000000000000000000000000000 4
b1111111111111111111111111110111000000000000000000000000000000000 B
b1000000100000000000010000110011 +
b1000000100000000000010000110011 ;
b1000000100000000000010000110011 =
b0 (
b0 2
b0 F
b100100 *
b100100 ?
b100000 )
b100000 >
b100000 @
b1000 #
1!
#400000
0!
#425000
b1000111111111111111111111111100101010 -
b1000111111111111111111111111100101010 4
b1000111111111111111111111111100101010 B
b1001 0
b1001 3
b1001 8
1.
b11 /
b11 7
b11 :
b1111111111111111111111111110111000000000000000000000000000000000 (
b1111111111111111111111111110111000000000000000000000000000000000 2
b1111111111111111111111111110111000000000000000000000000000000000 F
b1111111111111111111111111111111111111111111111111111111100101010 1
b1111001 6
b100 5
b10011 9
b1001 A
b1010 D
b1000 C
b1111111111111111111111111111111111111111111111111111111100101010 ,
b1111111111111111111111111111111111111111111111111111111100101010 <
b0 '
b0 E
b11110010101001000100010010010011 +
b11110010101001000100010010010011 ;
b11110010101001000100010010010011 =
b101000 *
b101000 ?
b100100 )
b100100 >
b100100 @
b1001 #
1!
#450000
0!
#475000
b1000111111111111111111111111110101111 -
b1000111111111111111111111111110101111 4
b1000111111111111111111111111110101111 B
b1010 0
b1010 3
b1010 8
b1000111111111111111111111111100101010 (
b1000111111111111111111111111100101010 2
b1000111111111111111111111111100101010 F
b10001111 1
b100 6
b110 5
b1111 D
b1001 C
b10001111 ,
b10001111 <
b1000111101001110010010010011 +
b1000111101001110010010010011 ;
b1000111101001110010010010011 =
b101100 *
b101100 ?
b101000 )
b101000 >
b101000 @
b1010 #
1!
#500000
0!
#525000
b1000111111111111111111111111110100101 -
b1000111111111111111111111111110100101 4
b1000111111111111111111111111110100101 B
b1011 0
b1011 3
b1011 8
b1111111111111111111111111111111111111111111111111111111111110101 1
b1111111 6
b111 5
b10101 D
b1111111111111111111111111111111111111111111111111111111111110101 ,
b1111111111111111111111111111111111111111111111111111111111110101 <
b1000111111111111111111111111110101111 (
b1000111111111111111111111111110101111 2
b1000111111111111111111111111110101111 F
b11111111010101001111010010010011 +
b11111111010101001111010010010011 ;
b11111111010101001111010010010011 =
b110000 *
b110000 ?
b101100 )
b101100 >
b101100 @
b1011 #
1!
#550000
0!
#575000
b10001111111111111111111111111101001010 -
b10001111111111111111111111111101001010 4
b10001111111111111111111111111101001010 B
b1000111111111111111111111111110100101 1
b0 0
b0 3
b0 8
0.
b10 /
b10 7
b10 :
b1000111111111111111111111111110100101 '
b1000111111111111111111111111110100101 E
b0 6
b0 5
b110011 9
b1010 A
b1001 D
b100101001000010100110011 +
b100101001000010100110011 ;
b100101001000010100110011 =
b1000111111111111111111111111110100101 (
b1000111111111111111111111111110100101 2
b1000111111111111111111111111110100101 F
b110100 *
b110100 ?
b110000 )
b110000 >
b110000 @
b1100 #
1!
#600000
0!
#625000
b1111111111111111111111111110111000000000000000000000000001011011 -
b1111111111111111111111111110111000000000000000000000000001011011 4
b1111111111111111111111111110111000000000000000000000000001011011 B
b10001111111111111111111111111101001010 1
b1 0
b1 3
b1 8
b10001111111111111111111111111101001010 '
b10001111111111111111111111111101001010 E
b100000 6
b1001 A
b1010 D
b1000000101001001000010010110011 +
b1000000101001001000010010110011 ;
b1000000101001001000010010110011 =
b111000 *
b111000 ?
b110100 )
b110100 >
b110100 @
b1101 #
1!
#650000
0!
#675000
b0 1
b0 0
b0 3
b0 8
b0 '
b0 E
b0 6
b11111 A
b0 D
b1000 C
b1111111111111111111111111110111000000000000000000000000000000000 -
b1111111111111111111111111110111000000000000000000000000000000000 4
b1111111111111111111111111110111000000000000000000000000000000000 B
b1000000111110110011 +
b1000000111110110011 ;
b1000000111110110011 =
b1111111111111111111111111110111000000000000000000000000000000000 (
b1111111111111111111111111110111000000000000000000000000000000000 2
b1111111111111111111111111110111000000000000000000000000000000000 F
b111100 *
b111100 ?
b111000 )
b111000 >
b111000 @
b1110 #
1!
#700000
0!
#725000
b1111111111111111111111111101110000000000000000000000000000000000 -
b1111111111111111111111111101110000000000000000000000000000000000 4
b1111111111111111111111111101110000000000000000000000000000000000 B
b1111111111111111111111111110111000000000000000000000000000000000 1
b1111111111111111111111111110111000000000000000000000000000000000 '
b1111111111111111111111111110111000000000000000000000000000000000 E
b11100 A
b11111 D
b11111 C
b1111111111000111000110011 +
b1111111111000111000110011 ;
b1111111111000111000110011 =
b1000000 *
b1000000 ?
b111100 )
b111100 >
b111100 @
b1111 #
1!
#750000
0!
#775000
b1111111111111111111111111110111000000000000000000000000000000000 -
b1111111111111111111111111110111000000000000000000000000000000000 4
b1111111111111111111111111110111000000000000000000000000000000000 B
b1 0
b1 3
b1 8
b1111111111111111111111111101110000000000000000000000000000000000 (
b1111111111111111111111111101110000000000000000000000000000000000 2
b1111111111111111111111111101110000000000000000000000000000000000 F
b100000 6
b11011 A
b11100 C
b1000001111111100000110110110011 +
b1000001111111100000110110110011 ;
b1000001111111100000110110110011 =
b1000100 *
b1000100 ?
b1000000 )
b1000000 >
b1000000 @
b10000 #
1!
#800000
0!
#825000
b1111111111111111111111111111111111111011100000000000000000000000 -
b1111111111111111111111111111111111111011100000000000000000000000 4
b1111111111111111111111111111111111111011100000000000000000000000 B
b10001111111111111111111111111101001010 1
b111 0
b111 3
b111 8
b10001111111111111111111111111101001010 '
b10001111111111111111111111111101001010 E
b1111111111111111111111111110111000000000000000000000000000000000 (
b1111111111111111111111111110111000000000000000000000000000000000 2
b1111111111111111111111111110111000000000000000000000000000000000 F
b101 5
b11010 A
b1010 D
b11011 C
b1000000101011011101110100110011 +
b1000000101011011101110100110011 ;
b1000000101011011101110100110011 =
b1001000 *
b1001000 ?
b1000100 )
b1000100 >
b1000100 @
b10001 #
1!
#850000
0!
#875000
b1 1
b1111111111111111111111111111111111111011100000000000000000000001 -
b1111111111111111111111111111111111111011100000000000000000000001 4
b1111111111111111111111111111111111111011100000000000000000000001 B
b1000 0
b1000 3
b1000 8
1.
b11 /
b11 7
b11 :
b0 '
b0 E
b1111111111111111111111111111111111111011100000000000000000000000 (
b1111111111111111111111111111111111111011100000000000000000000000 2
b1111111111111111111111111111111111111011100000000000000000000000 F
b0 6
b0 5
b10011 9
b1100 A
b1 D
b11010 C
b1 ,
b1 <
b111010000011000010011 +
b111010000011000010011 ;
b111010000011000010011 =
b1001100 *
b1001100 ?
b1001000 )
b1001000 >
b1001000 @
b10010 #
1!
#900000
0!
#925000
b1111111111111111111111111111111111111011011111111111111111110111 -
b1111111111111111111111111111111111111011011111111111111111110111 4
b1111111111111111111111111111111111111011011111111111111111110111 B
b1111111111111111111111111111111111111011100000000000000000000001 (
b1111111111111111111111111111111111111011100000000000000000000001 2
b1111111111111111111111111111111111111011100000000000000000000001 F
b1111111111111111111111111111111111111111111111111111111111110110 1
b1111111 6
b1101 A
b10110 D
b1100 C
b1111111111111111111111111111111111111111111111111111111111110110 ,
b1111111111111111111111111111111111111111111111111111111111110110 <
b11111111011001100000011010010011 +
b11111111011001100000011010010011 ;
b11111111011001100000011010010011 =
b1010000 *
b1010000 ?
b1001100 )
b1001100 >
b1001100 @
b10011 #
1!
#950000
0!
#975000
b1111111111111111111111111111111111111011011111111111111111110111 1
b111111111 -
b111111111 4
b111111111 B
b110 0
b110 3
b110 8
0.
b10 /
b10 7
b10 :
b1111111111111111111111111111111111111011011111111111111111110111 '
b1111111111111111111111111111111111111011011111111111111111110111 E
b1111111111111111111111111111111111111011011111111111111111110111 (
b1111111111111111111111111111111111111011011111111111111111110111 2
b1111111111111111111111111111111111111011011111111111111111110111 F
b0 6
b101 5
b110011 9
b1110 A
b1101 D
b1101 C
b110101101101011100110011 +
b110101101101011100110011 ;
b110101101101011100110011 =
b1010100 *
b1010100 ?
b1010000 )
b1010000 >
b1010000 @
b10100 #
1!
#1000000
0!
#1025000
b0 1
b111111111 -
b111111111 4
b111111111 B
b1000 0
b1000 3
b1000 8
1.
b11 /
b11 7
b11 :
b0 '
b0 E
b111111111 (
b111111111 2
b111111111 F
b0 5
b10011 9
b1011 A
b0 D
b1110 C
b0 ,
b0 <
b1110000010110010011 +
b1110000010110010011 ;
b1110000010110010011 =
b1011000 *
b1011000 ?
b1010100 )
b1010100 >
b1010100 @
b10101 #
1!
#1050000
0!
#1075000
b0 -
b0 4
b0 B
b0 (
b0 2
b0 F
b0 A
b0 C
b10011 +
b10011 ;
b10011 =
b1011100 *
b1011100 ?
b1011000 )
b1011000 >
b1011000 @
b10110 #
1!
#1100000
0!
#1125000
b111111111 1
b1111111111111111111111111110111000000000000000000000000110100100 -
b1111111111111111111111111110111000000000000000000000000110100100 4
b1111111111111111111111111110111000000000000000000000000110100100 B
b10 0
b10 3
b10 8
0.
b10 /
b10 7
b10 :
b111111111 '
b111111111 E
b1111111111111111111111111110111000000000000000000000000001011011 (
b1111111111111111111111111110111000000000000000000000000001011011 2
b1111111111111111111111111110111000000000000000000000000001011011 F
b100 5
b110011 9
b1111 A
b1011 D
b1001 C
b101101001100011110110011 +
b101101001100011110110011 ;
b101101001100011110110011 =
b1100000 *
b1100000 ?
b1011100 )
b1011100 >
b1011100 @
b10111 #
1!
#1150000
0!
#1175000
b1111111111111111111111111110111000000000000000000000000000000000 -
b1111111111111111111111111110111000000000000000000000000000000000 4
b1111111111111111111111111110111000000000000000000000000000000000 B
b1111111111111111111111111110111000000000000000000000000110100100 1
b100 0
b100 3
b100 8
b1111111111111111111111111110111000000000000000000000000110100100 '
b1111111111111111111111111110111000000000000000000000000110100100 E
b111 5
b10000 A
b1111 D
b111101001111100000110011 +
b111101001111100000110011 ;
b111101001111100000110011 =
b1100100 *
b1100100 ?
b1100000 )
b1100000 >
b1100000 @
b11000 #
1!
#1200000
0!
#1225000
b100001 1
b1111111111111111111111111111111111111111111111111111111111110111 -
b1111111111111111111111111111111111111111111111111111111111110111 4
b1111111111111111111111111111111111111111111111111111111111110111 B
b1110 0
b1110 3
b1110 8
1.
b11 /
b11 7
b11 :
b0 '
b0 E
b1111111111111111111111111110111000000000000000000000000000000000 (
b1111111111111111111111111110111000000000000000000000000000000000 2
b1111111111111111111111111110111000000000000000000000000000000000 F
b100001 6
b101 5
b10011 9
b1 D
b10000 C
b100001 ,
b100001 <
b1000010000110000101100000010011 +
b1000010000110000101100000010011 ;
b1000010000110000101100000010011 =
b1101000 *
b1101000 ?
b1100100 )
b1100100 >
b1100100 @
b11001 #
1!
#1250000
0!
#1275000
b1101 0
b1101 3
b1101 8
b1 1
b0 6
b10001 A
b1 ,
b1 <
b111111111111111111111111111111111111111111111111111111111111011 -
b111111111111111111111111111111111111111111111111111111111111011 4
b111111111111111111111111111111111111111111111111111111111111011 B
b110000101100010010011 +
b110000101100010010011 ;
b110000101100010010011 =
b1111111111111111111111111111111111111111111111111111111111110111 (
b1111111111111111111111111111111111111111111111111111111111110111 2
b1111111111111111111111111111111111111111111111111111111111110111 F
b1101100 *
b1101100 ?
b1101000 )
b1101000 >
b1101000 @
b11010 #
1!
#1300000
0!
#1325000
b1111111111111111111111111111111111111111111111111111111111110110 -
b1111111111111111111111111111111111111111111111111111111111110110 4
b1111111111111111111111111111111111111111111111111111111111110110 B
b1100 0
b1100 3
b1100 8
b111111111111111111111111111111111111111111111111111111111111011 (
b111111111111111111111111111111111111111111111111111111111111011 2
b111111111111111111111111111111111111111111111111111111111111011 F
b1 5
b10001 C
b110001001100010010011 +
b110001001100010010011 ;
b110001001100010010011 =
b1110000 *
b1110000 ?
b1101100 )
b1101100 >
b1101100 @
b11011 #
1!
#1350000
0!
#1375000
b1000 0
b1000 3
b1000 8
b0 1
b0 5
b0 A
b0 D
b0 C
b0 ,
b0 <
b0 -
b0 4
b0 B
b10011 +
b10011 ;
b10011 =
b0 (
b0 2
b0 F
b1110100 *
b1110100 ?
b1110000 )
b1110000 >
b1110000 @
b11100 #
1!
#1400000
0!
#1425000
b1111000 *
b1111000 ?
b1110100 )
b1110100 >
b1110100 @
b11101 #
1!
#1450000
0!
#1475000
b1111100 *
b1111100 ?
b1111000 )
b1111000 >
b1111000 @
b11110 #
1!
#1500000
0!
#1525000
b10000000 *
b10000000 ?
b1111100 )
b1111100 >
b1111100 @
1!
